parallel_db/__init__.py
parallel_db/base/__init__.py
parallel_db/base/abstract_table.py
parallel_db/base/base_scenario.py
parallel_db/base/base_table.py
parallel_db/db_connection/connection.py
parallel_db/db_connection/connection_factory.py
parallel_db/db_connection/cooked_connections.py
parallel_db/db_connection/default_connections.py
parallel_db/decorators/__init__.py
parallel_db/decorators/utils.py
parallel_db/logger/__init__.py
parallel_db/time_predictor/__init__.py
parallel_db/time_predictor/time_predictor.py
parallel_db-0.0.3.post2.dist-info/METADATA
parallel_db-0.0.3.post2.dist-info/WHEEL
parallel_db-0.0.3.post2.dist-info/licenses/LICENSE
parallel_db-0.0.3.post2.dist-info/RECORD
