Metadata-Version: 2.1
Name: parallel_db
Version: 0.0.3.post2
Summary: Package for high level database parallel  automatization
Project-URL: Homepage, https://github.com/Zkh-dot/parallel-db
Project-URL: Issues, https://github.com/Zkh-dot/parallel-db/issues
Author-email: zkh-dot <kernzahar@gmail.com>
License-File: LICENSE
Classifier: License :: OSI Approved :: MIT License
Classifier: Operating System :: OS Independent
Classifier: Programming Language :: Python :: 3
Requires-Python: >=3.10
